bookworm/__init__.py
bookworm/__main__.py
bookworm/definitions.py
cli/__init__.py
cli/book_parser.py
cli/goal_parser.py
cli/parser.py
cli/prompt.py
cli/recommendation.py
cli/validate.py
database/__init__.py
database/books.py
database/db.py
database/goals.py
lib/__init__.py
lib/audiobook.py
lib/audiobookseconds.py
lib/book.py
lib/ebook.py
lib/format.py
lib/goal.py
lib/goal_tracker.py
lib/ibook.py
lib/shelf.py
bkwrm-0.2.0.0.dist-info/LICENCE
bkwrm-0.2.0.0.dist-info/METADATA
bkwrm-0.2.0.0.dist-info/WHEEL
bkwrm-0.2.0.0.dist-info/entry_points.txt
bkwrm-0.2.0.0.dist-info/top_level.txt
bkwrm-0.2.0.0.dist-info/RECORD
