Metadata-Version: 2.1
Name: bkwrm
Version: 0.2.0.0
Summary: Keep track of your progress towards your book-reading goal.
Home-page: https://github.com/aamirza/bookworm
Author: Aamir Mirza
License: MIT
Platform: UNKNOWN
Classifier: Programming Language :: Python :: 3
Classifier: Programming Language :: Python :: 3.7
Requires-Python: >=3.7
